flask_turnstile.py
Flask_Turnstile-0.1.1.dist-info/LICENSE
Flask_Turnstile-0.1.1.dist-info/METADATA
Flask_Turnstile-0.1.1.dist-info/WHEEL
Flask_Turnstile-0.1.1.dist-info/top_level.txt
Flask_Turnstile-0.1.1.dist-info/RECORD
